{
  "kind": "collectionType",
  "collectionName": "services",
  "info": {
    "name": "Services",
    "description": ""
  },
  "options": {
    "increments": true,
    "timestamps": true,
    "draftAndPublish": true
  },
  "pluginOptions": {},
  "attributes": {
    "title": {
      "type": "string"
    },
    "content": {
      "type": "richtext"
    },
    "slug": {
      "type": "uid",
      "targetField": "title"
    },
    "subBanner": {
      "type": "component",
      "repeatable": false,
      "component": "page-services.sub-banner-services"
    },
    "metaTags": {
      "type": "component",
      "repeatable": false,
      "component": "seo.meta-tags"
    },
    "thumbnail": {
      "model": "file",
      "via": "related",
      "allowedTypes": [
        "images",
        "files",
        "videos"
      ],
      "plugin": "upload",
      "required": false,
      "pluginOptions": {}
    },
    "partnerLogos": {
      "collection": "file",
      "via": "related",
      "allowedTypes": [
        "images",
        "files",
        "videos"
      ],
      "plugin": "upload",
      "required": false,
      "pluginOptions": {}
    }
  }
}
